masterthesis/__init__.py
masterthesis/beta_decay.py
masterthesis/beta_gen.py
masterthesis/cockpit.py
masterthesis/constants.py
masterthesis/dataset.py
masterthesis/fitting.py
masterthesis/model_eval.py
masterthesis/model_pipeline.py
masterthesis/models.py
luca_fallboehmer_masterthesis-0.0.2.dist-info/LICENSE
luca_fallboehmer_masterthesis-0.0.2.dist-info/METADATA
luca_fallboehmer_masterthesis-0.0.2.dist-info/WHEEL
luca_fallboehmer_masterthesis-0.0.2.dist-info/top_level.txt
luca_fallboehmer_masterthesis-0.0.2.dist-info/RECORD
